pytest_jux/__init__.py
pytest_jux/api_client.py
pytest_jux/canonicalizer.py
pytest_jux/config.py
pytest_jux/errors.py
pytest_jux/metadata.py
pytest_jux/plugin.py
pytest_jux/signer.py
pytest_jux/storage.py
pytest_jux/verifier.py
pytest_jux/commands/__init__.py
pytest_jux/commands/cache.py
pytest_jux/commands/config_cmd.py
pytest_jux/commands/inspect.py
pytest_jux/commands/keygen.py
pytest_jux/commands/publish.py
pytest_jux/commands/sign.py
pytest_jux/commands/verify.py
pytest_jux-0.4.1.dist-info/licenses/LICENSE
pytest_jux-0.4.1.dist-info/licenses/NOTICE
pytest_jux-0.4.1.dist-info/METADATA
pytest_jux-0.4.1.dist-info/WHEEL
pytest_jux-0.4.1.dist-info/entry_points.txt
pytest_jux-0.4.1.dist-info/top_level.txt
pytest_jux-0.4.1.dist-info/RECORD
