Metadata-Version: 2.4
Name: pytest-jux
Version: 0.4.1
Summary: A pytest plugin for signing and publishing JUnit XML test reports to the Jux REST API
Author-email: Georges Martin <jrjsmrtn@gmail.com>
License: Apache-2.0
Project-URL: Homepage, https://github.com/jrjsmrtn/pytest-jux
Project-URL: Documentation, https://github.com/jrjsmrtn/pytest-jux/tree/main/docs
Project-URL: Repository, https://github.com/jrjsmrtn/pytest-jux
Project-URL: Issues, https://github.com/jrjsmrtn/pytest-jux/issues
Project-URL: Security, https://github.com/jrjsmrtn/pytest-jux/blob/main/docs/security/SECURITY.md
Keywords: pytest,junit-xml,xml-signature,test-reporting,jux,security
Classifier: Development Status :: 3 - Alpha
Classifier: Framework :: Pytest
Classifier: Intended Audience :: Developers
Classifier: Intended Audience :: System Administrators
Classifier: License :: OSI Approved :: Apache Software License
Classifier: Operating System :: POSIX :: Linux
Classifier: Programming Language :: Python :: 3
Classifier: Programming Language :: Python :: 3.11
Classifier: Programming Language :: Python :: 3.12
Classifier: Topic :: Software Development :: Testing
Classifier: Topic :: System :: Systems Administration
Classifier: Topic :: Security :: Cryptography
Requires-Python: >=3.11
License-File: LICENSE
License-File: NOTICE
Requires-Dist: lxml>=5.0
Requires-Dist: xmlschema>=2.5
Requires-Dist: signxml>=3.2
Requires-Dist: cryptography>=41.0
Requires-Dist: pytest>=7.4
Requires-Dist: pytest-metadata>=3.0
Requires-Dist: configargparse>=1.7
Requires-Dist: rich>=13.0
Requires-Dist: requests>=2.31
Requires-Dist: pydantic>=2.5
Provides-Extra: dev
Requires-Dist: ruff>=0.1; extra == "dev"
Requires-Dist: mypy>=1.7; extra == "dev"
Requires-Dist: pytest-cov>=4.1; extra == "dev"
Requires-Dist: pytest-mock>=3.12; extra == "dev"
Requires-Dist: pytest-xdist>=3.5; extra == "dev"
Requires-Dist: coverage[toml]>=7.3; extra == "dev"
Requires-Dist: types-requests>=2.31; extra == "dev"
Requires-Dist: responses>=0.25; extra == "dev"
Requires-Dist: hypothesis>=6.92; extra == "dev"
Requires-Dist: pre-commit>=3.5; extra == "dev"
Provides-Extra: security
Requires-Dist: pip-audit>=2.6; extra == "security"
Requires-Dist: safety>=3.0; extra == "security"
Provides-Extra: docs
Requires-Dist: sphinx>=8.0; extra == "docs"
Requires-Dist: myst-parser>=4.0; extra == "docs"
Requires-Dist: sphinx-argparse-cli>=1.18; extra == "docs"
Requires-Dist: sphinx-autodoc-typehints>=2.0; extra == "docs"
Requires-Dist: furo>=2024.0; extra == "docs"
Dynamic: license-file
